litepali/__init__.py
litepali/model.py
litepali-0.0.5.dist-info/LICENSE
litepali-0.0.5.dist-info/METADATA
litepali-0.0.5.dist-info/WHEEL
litepali-0.0.5.dist-info/top_level.txt
litepali-0.0.5.dist-info/RECORD
