Metadata-Version: 2.1
Name: litepali
Version: 0.0.5
Summary: Lightweight ColPali-based retrieval for cloud
Author-email: Simeon Emanuilov <simeon.emanuilov@gmail.com>
License: MIT License
Project-URL: Homepage, https://github.com/s-emanuilov/litepali
Project-URL: Website, https://litepali.com
Project-URL: Bug Tracker, https://github.com/s-emanuilov/litepali/issues
Keywords: colpali,image retrieval,rag,semantic search,vision-language-models,document-ai,multi-modal,information retrieval,machine learning,cloud-optimized
Classifier: Development Status :: 3 - Alpha
Classifier: Intended Audience :: Developers
Classifier: Intended Audience :: Science/Research
Classifier: Topic :: Scientific/Engineering :: Artificial Intelligence
Classifier: Topic :: Scientific/Engineering :: Image Recognition
Classifier: Topic :: Text Processing :: Indexing
Classifier: Topic :: Software Development :: Libraries :: Python Modules
Classifier: Programming Language :: Python :: 3
Classifier: Programming Language :: Python :: 3.8
Classifier: Programming Language :: Python :: 3.9
Classifier: Programming Language :: Python :: 3.10
Classifier: Programming Language :: Python :: 3.11
Classifier: License :: OSI Approved :: MIT License
Classifier: Operating System :: OS Independent
Requires-Python: >=3.8
License-File: LICENSE
Requires-Dist: colpali-engine<0.4.0,>=0.3.0
